pytest_pikachu/__init__.py
pytest_pikachu/plugin.py
pytest_pikachu-1.0.0.dist-info/LICENSE
pytest_pikachu-1.0.0.dist-info/METADATA
pytest_pikachu-1.0.0.dist-info/WHEEL
pytest_pikachu-1.0.0.dist-info/entry_points.txt
pytest_pikachu-1.0.0.dist-info/top_level.txt
pytest_pikachu-1.0.0.dist-info/RECORD
