Metadata-Version: 2.1
Name: pytest-pikachu
Version: 1.0.0
Summary: Show surprise when tests are passing
Home-page: https://github.com/chornsby/pytest-pikachu
Author: Charlie Hornsby
Author-email: charlie.hornsby@hotmail.co.uk
License: MIT
Platform: UNKNOWN
Classifier: Development Status :: 5 - Production/Stable
Classifier: Framework :: Pytest
Classifier: Intended Audience :: Developers
Classifier: Topic :: Software Development :: Testing
Classifier: Programming Language :: Python
Classifier: Programming Language :: Python :: 3
Classifier: Programming Language :: Python :: 3.6
Classifier: Programming Language :: Python :: 3.7
Classifier: Programming Language :: Python :: 3.8
Classifier: Programming Language :: Python :: 3.9
Classifier: Programming Language :: Python :: Implementation :: CPython
Classifier: Programming Language :: Python :: Implementation :: PyPy
Classifier: Operating System :: OS Independent
Classifier: License :: OSI Approved :: MIT License
License-File: LICENSE
Requires-Dist: pytest
